alibabacloud_alimt20181012/__init__.py
alibabacloud_alimt20181012/client.py
alibabacloud_alimt20181012/models.py
alibabacloud_alimt20181012_py2-1.2.1.dist-info/LICENSE
alibabacloud_alimt20181012_py2-1.2.1.dist-info/METADATA
alibabacloud_alimt20181012_py2-1.2.1.dist-info/WHEEL
alibabacloud_alimt20181012_py2-1.2.1.dist-info/top_level.txt
alibabacloud_alimt20181012_py2-1.2.1.dist-info/RECORD
